propy/__init__.py
propy/wrappers/__init__.py
propy/wrappers/methods.py
propy/wrappers/methods_test.py
propy/wrappers/properties.py
propy/wrappers/properties_test.py
propy-1.0.0.dist-info/LICENSE.txt
propy-1.0.0.dist-info/METADATA
propy-1.0.0.dist-info/RECORD
propy-1.0.0.dist-info/WHEEL
propy-1.0.0.dist-info/top_level.txt
