Metadata-Version: 2.1
Name: propy
Version: 1.0.0
Summary: Library of class property creation functions for type conversion and validation.
Home-page: https://github.com/mpewsey/propy
Author: Matt Pewsey
License: BSD 3-Clause License
Keywords: properties,utility
Platform: UNKNOWN
Classifier: Programming Language :: Python :: 2.7
Classifier: Programming Language :: Python :: 3.5
Classifier: Programming Language :: Python :: 3.6
Classifier: Operating System :: OS Independent
Classifier: License :: OSI Approved :: BSD License
Requires-Python: >=2.7,!=3.0,!=3.1,!=3.2,!=3.3,!=3.4
Provides-Extra: test
Provides-Extra: docs
Provides-Extra: docs
Requires-Dist: docutils (==0.14); extra == 'docs'
Requires-Dist: numpydoc (>=0.8.0); extra == 'docs'
Provides-Extra: test
Requires-Dist: pytest (>=3.5.1); extra == 'test'
Requires-Dist: pytest-cov (>=2.5.1); extra == 'test'
Requires-Dist: codecov (>=2.0.15); extra == 'test'
Requires-Dist: numpy (>=1.14.5); extra == 'test'
